async_files/__init__.py
async_files/fileio.py
async_files/fileobj.py
async_files/gzip.py
async_files/tempfile.py
async_files/utils.py
examples/__init__.py
examples/basic_example.py
examples/tarfile_example.py
examples/tempfile_example.py
examples/utils.py
tests/__init__.py
tests/test_fileio.py
tests/test_other_fileio.py
tests/utils.py
async_files-0.4.dist-info/LICENSE
async_files-0.4.dist-info/METADATA
async_files-0.4.dist-info/WHEEL
async_files-0.4.dist-info/top_level.txt
async_files-0.4.dist-info/RECORD
