Metadata-Version: 2.1
Name: async-files
Version: 0.4
Summary: Async Files
Home-page: https://github.com/Niraj-Kamdar/async-files
Author: Niraj Kamdar
License: MIT
Download-URL: https://github.com/Niraj-Kamdar/async-files/archive/master.zip
Keywords: asyncio,file,aiofile
Platform: UNKNOWN
Classifier: Development Status :: 4 - Beta
Classifier: Intended Audience :: Developers
Classifier: Topic :: Software Development :: Build Tools
Classifier: Natural Language :: English
Classifier: Operating System :: OS Independent
Classifier: License :: OSI Approved :: MIT License
Classifier: Programming Language :: Python :: 3
Classifier: Programming Language :: Python :: 3.6
Classifier: Programming Language :: Python :: 3.7
Classifier: Programming Language :: Python :: 3.8
